tabpfn/__init__.py
tabpfn/base.py
tabpfn/classifier.py
tabpfn/constants.py
tabpfn/errors.py
tabpfn/inference.py
tabpfn/inference_config.py
tabpfn/inference_tuning.py
tabpfn/model_loading.py
tabpfn/parallel_execute.py
tabpfn/regressor.py
tabpfn/settings.py
tabpfn/utils.py
tabpfn/validation.py
tabpfn/architectures/__init__.py
tabpfn/architectures/interface.py
tabpfn/architectures/base/__init__.py
tabpfn/architectures/base/bar_distribution.py
tabpfn/architectures/base/config.py
tabpfn/architectures/base/encoders.py
tabpfn/architectures/base/layer.py
tabpfn/architectures/base/memory.py
tabpfn/architectures/base/mlp.py
tabpfn/architectures/base/tabpfn_col_embedding.pt
tabpfn/architectures/base/thinking_tokens.py
tabpfn/architectures/base/transformer.py
tabpfn/architectures/base/attention/__init__.py
tabpfn/architectures/base/attention/full_attention.py
tabpfn/finetuning/__init__.py
tabpfn/finetuning/_torch_compat.py
tabpfn/finetuning/data_util.py
tabpfn/finetuning/finetuned_base.py
tabpfn/finetuning/finetuned_classifier.py
tabpfn/finetuning/finetuned_regressor.py
tabpfn/finetuning/train_util.py
tabpfn/misc/_sklearn_compat.py
tabpfn/misc/debug_versions.py
tabpfn/model/__init__.py
tabpfn/model/attention.py
tabpfn/model/bar_distribution.py
tabpfn/model/config.py
tabpfn/model/encoders.py
tabpfn/model/layer.py
tabpfn/model/loading.py
tabpfn/model/memory.py
tabpfn/model/mlp.py
tabpfn/model/preprocessing.py
tabpfn/model/transformer.py
tabpfn/preprocessing/__init__.py
tabpfn/preprocessing/clean.py
tabpfn/preprocessing/configs.py
tabpfn/preprocessing/ensemble.py
tabpfn/preprocessing/initialization.py
tabpfn/preprocessing/modality_detection.py
tabpfn/preprocessing/pipeline.py
tabpfn/preprocessing/presets.py
tabpfn/preprocessing/transform.py
tabpfn/preprocessing/type_detection.py
tabpfn/preprocessing/steps/__init__.py
tabpfn/preprocessing/steps/adaptive_quantile_transformer.py
tabpfn/preprocessing/steps/add_fingerprint_features_step.py
tabpfn_fork-6.3.4.dist-info/licenses/LICENSE
tabpfn_fork-6.3.4.dist-info/METADATA
tabpfn_fork-6.3.4.dist-info/WHEEL
tabpfn_fork-6.3.4.dist-info/top_level.txt
tabpfn_fork-6.3.4.dist-info/RECORD
